CHANGES.rst
LICENSE
MANIFEST.in
README.rst
setup.py
ApiDoc.egg-info/PKG-INFO
ApiDoc.egg-info/SOURCES.txt
ApiDoc.egg-info/dependency_links.txt
ApiDoc.egg-info/entry_points.txt
ApiDoc.egg-info/requires.txt
ApiDoc.egg-info/top_level.txt
apidoc/__init__.py
apidoc/command/__init__.py
apidoc/command/run.py
apidoc/factory/__init__.py
apidoc/factory/config.py
apidoc/factory/template.py
apidoc/factory/source/__init__.py
apidoc/factory/source/category.py
apidoc/factory/source/configuration.py
apidoc/factory/source/element.py
apidoc/factory/source/method.py
apidoc/factory/source/object.py
apidoc/factory/source/parameter.py
apidoc/factory/source/responseCode.py
apidoc/factory/source/root.py
apidoc/factory/source/rootDto.py
apidoc/factory/source/type.py
apidoc/factory/source/version.py
apidoc/lib/__init__.py
apidoc/lib/fswatcher/__init__.py
apidoc/lib/fswatcher/callbackHandler.py
apidoc/lib/fswatcher/event.py
apidoc/lib/fswatcher/observer.py
apidoc/lib/util/__init__.py
apidoc/lib/util/cast.py
apidoc/lib/util/decorator.py
apidoc/lib/util/enum.py
apidoc/lib/util/serialize.py
apidoc/object/__init__.py
apidoc/object/config.py
apidoc/object/source_dto.py
apidoc/object/source_raw.py
apidoc/object/source_sample.py
apidoc/service/__init__.py
apidoc/service/config.py
apidoc/service/extender.py
apidoc/service/merger.py
apidoc/service/parser.py
apidoc/service/source.py
apidoc/service/template.py
apidoc/service/validator.py
apidoc/settings/logging.yml
apidoc/settings/schemas/config.yml
apidoc/settings/schemas/source.yml
apidoc/template/default.html
apidoc/template/helper/code.html
apidoc/template/helper/diff.html
apidoc/template/helper/util.html
apidoc/template/layout/content-only.html
apidoc/template/layout/default.html
apidoc/template/partial/help.html
apidoc/template/partial/method_category.html
apidoc/template/partial/method_diff.html
apidoc/template/partial/method_sample.html
apidoc/template/partial/navigation.html
apidoc/template/partial/type_category.html
apidoc/template/partial/type_diff.html
apidoc/template/partial/type_sample.html
apidoc/template/resource/css/combined-embedded.css
apidoc/template/resource/css/combined.css
