Metadata-Version: 1.1
Name: ApiDoc
Version: 1.4.0
Summary: Api Documentation Generator
Home-page: http://solutionscloud.github.io/apidoc/
Author: Jérémy Derussé
Author-email: jeremy.derusse@sfr.com
License: GPLv3+
Platform: Any
Classifier: Development Status :: 5 - Production/Stable
Classifier: Environment :: Console
Classifier: Intended Audience :: Developers
Classifier: License :: OSI Approved :: GNU General Public License v3 or later (GPLv3+)
Classifier: Natural Language :: English
Classifier: Operating System :: MacOS
Classifier: Operating System :: POSIX :: Linux
Classifier: Programming Language :: Python :: 3
Classifier: Programming Language :: Python :: 3.2
Classifier: Programming Language :: Python :: 3.3
Classifier: Topic :: Documentation
Classifier: Topic :: Software Development :: Documentation
